MANIFEST.in
README.md
cascmd.py
requirements.txt
setup.py
cas/__init__.py
cas/api.py
cas/archive.py
cas/client.py
cas/job.py
cas/multipart_upload.py
cas/response.py
cas/vault.py
cas/cas_cmd/__init__.py
cas/cas_cmd/cas_ops.py
cas/conf/__init__.py
cas/conf/client_conf.py
cas/conf/common_conf.py
cas/conf/multi_task_conf.py
cas/exceptions/__init__.py
cas/exceptions/cas_client_error.py
cas/exceptions/cas_server_error.py
cas/utils/__init__.py
cas/utils/file_utils.py
cas/utils/http_utils.py
cas/utils/merkle.py
cassdk.egg-info/PKG-INFO
cassdk.egg-info/SOURCES.txt
cassdk.egg-info/dependency_links.txt
cassdk.egg-info/top_level.txt