Metadata-Version: 1.0
Name: cassdk
Version: 1.0.2
Summary: Python SDK and cmd tools for Tencent CAS (Cloud Archive Service)
Home-page: https://www.qcloud.com/
Author: Tencent CAS team
Author-email: iainyu@tencent.com
License: MIT License
Platform: UNKNOWN
